Workbook

Sheet P&L
A1: ="P&L за "&Настройки!B3&" год"
A2: Всё считается автоматически. Год меняется на листе «Настройки». Заполняйте только «Продажи» и «Расходы».
A4: Период | B4: Заказов | C4: Поздравлений, шт | D4: Выручка, $ | E4: Средний чек, $ | F4: Реклама / продвижение | G4: Подрядчики / монтаж | H4: Сервисы и подписки | I4: Оборудование | J4: Комиссии банка | K4: Прочее | L4: Расходы итого, $ | M4: Налог, $ | N4: Комиссия, $ | O4: Чистая прибыль, $ | P4: Маржа, %
A5: Январь | B5: =COUNTIFS(Продажи!$A$2:$A$5000,">="&DATE(Настройки!$B$3,1,1),Продажи!$A$2:$A$5000,"<"&DATE(Настройки!$B$3,2,1),Продажи!$F$2:$F$5000,">0") | C5: =SUMIFS(Продажи!$D$2:$D$5000,Продажи!$A$2:$A$5000,">="&DATE(Настройки!$B$3,1,1),Продажи!$A$2:$A$5000,"<"&DATE(Настройки!$B$3,2,1)) | D5: =SUMIFS(Продажи!$F$2:$F$5000,Продажи!$A$2:$A$5000,">="&DATE(Настройки!$B$3,1,1),Продажи!$A$2:$A$5000,"<"&DATE(Настройки!$B$3,2,1)) | E5: =IF(B5=0,0,D5/B5) | F5: =SUMIFS(Расходы!$D$2:$D$5000,Расходы!$A$2:$A$5000,">="&DATE(Настройки!$B$3,1,1),Расходы!$A$2:$A$5000,"<"&DATE(Настройки!$B$3,2,1),Расходы!$B$2:$B$5000,Настройки!$B$8) | G5: =SUMIFS(Расходы!$D$2:$D$5000,Расходы!$A$2:$A$5000,">="&DATE(Настройки!$B$3,1,1),Расходы!$A$2:$A$5000,"<"&DATE(Настройки!$B$3,2,1),Расходы!$B$2:$B$5000,Настройки!$B$9) | H5: =SUMIFS(Расходы!$D$2:$D$5000,Расходы!$A$2:$A$5000,">="&DATE(Настройки!$B$3,1,1),Расходы!$A$2:$A$5000,"<"&DATE(Настройки!$B$3,2,1),Расходы!$B$2:$B$5000,Настройки!$B$10) | I5: =SUMIFS(Расходы!$D$2:$D$5000,Расходы!$A$2:$A$5000,">="&DATE(Настройки!$B$3,1,1),Расходы!$A$2:$A$5000,"<"&DATE(Настройки!$B$3,2,1),Расходы!$B$2:$B$5000,Настройки!$B$11) | J5: =SUMIFS(Расходы!$D$2:$D$5000,Расходы!$A$2:$A$5000,">="&DATE(Настройки!$B$3,1,1),Расходы!$A$2:$A$5000,"<"&DATE(Настройки!$B$3,2,1),Расходы!$B$2:$B$5000,Настройки!$B$12) | K5: =SUMIFS(Расходы!$D$2:$D$5000,Расходы!$A$2:$A$5000,">="&DATE(Настройки!$B$3,1,1),Расходы!$A$2:$A$5000,"<"&DATE(Настройки!$B$3,2,1),Расходы!$B$2:$B$5000,Настройки!$B$13) | L5: =SUMIFS(Расходы!$D$2:$D$5000,Расходы!$A$2:$A$5000,">="&DATE(Настройки!$B$3,1,1),Расходы!$A$2:$A$5000,"<"&DATE(Настройки!$B$3,2,1)) | M5: =D5*Настройки!$B$4 | N5: =D5*Настройки!$B$5 | O5: =D5-L5-M5-N5 | P5: =IF(D5=0,0,O5/D5)
A6: Февраль | B6: =COUNTIFS(Продажи!$A$2:$A$5000,">="&DATE(Настройки!$B$3,2,1),Продажи!$A$2:$A$5000,"<"&DATE(Настройки!$B$3,3,1),Продажи!$F$2:$F$5000,">0") | C6: =SUMIFS(Продажи!$D$2:$D$5000,Продажи!$A$2:$A$5000,">="&DATE(Настройки!$B$3,2,1),Продажи!$A$2:$A$5000,"<"&DATE(Настройки!$B$3,3,1)) | D6: =SUMIFS(Продажи!$F$2:$F$5000,Продажи!$A$2:$A$5000,">="&DATE(Настройки!$B$3,2,1),Продажи!$A$2:$A$5000,"<"&DATE(Настройки!$B$3,3,1)) | E6: =IF(B6=0,0,D6/B6) | F6: =SUMIFS(Расходы!$D$2:$D$5000,Расходы!$A$2:$A$5000,">="&DATE(Настройки!$B$3,2,1),Расходы!$A$2:$A$5000,"<"&DATE(Настройки!$B$3,3,1),Расходы!$B$2:$B$5000,Настройки!$B$8) | G6: =SUMIFS(Расходы!$D$2:$D$5000,Расходы!$A$2:$A$5000,">="&DATE(Настройки!$B$3,2,1),Расходы!$A$2:$A$5000,"<"&DATE(Настройки!$B$3,3,1),Расходы!$B$2:$B$5000,Настройки!$B$9) | H6: =SUMIFS(Расходы!$D$2:$D$5000,Расходы!$A$2:$A$5000,">="&DATE(Настройки!$B$3,2,1),Расходы!$A$2:$A$5000,"<"&DATE(Настройки!$B$3,3,1),Расходы!$B$2:$B$5000,Настройки!$B$10) | I6: =SUMIFS(Расходы!$D$2:$D$5000,Расходы!$A$2:$A$5000,">="&DATE(Настройки!$B$3,2,1),Расходы!$A$2:$A$5000,"<"&DATE(Настройки!$B$3,3,1),Расходы!$B$2:$B$5000,Настройки!$B$11) | J6: =SUMIFS(Расходы!$D$2:$D$5000,Расходы!$A$2:$A$5000,">="&DATE(Настройки!$B$3,2,1),Расходы!$A$2:$A$5000,"<"&DATE(Настройки!$B$3,3,1),Расходы!$B$2:$B$5000,Настройки!$B$12) | K6: =SUMIFS(Расходы!$D$2:$D$5000,Расходы!$A$2:$A$5000,">="&DATE(Настройки!$B$3,2,1),Расходы!$A$2:$A$5000,"<"&DATE(Настройки!$B$3,3,1),Расходы!$B$2:$B$5000,Настройки!$B$13) | L6: =SUMIFS(Расходы!$D$2:$D$5000,Расходы!$A$2:$A$5000,">="&DATE(Настройки!$B$3,2,1),Расходы!$A$2:$A$5000,"<"&DATE(Настройки!$B$3,3,1)) | M6: =D6*Настройки!$B$4 | N6: =D6*Настройки!$B$5 | O6: =D6-L6-M6-N6 | P6: =IF(D6=0,0,O6/D6)
A7: Март | B7: =COUNTIFS(Продажи!$A$2:$A$5000,">="&DATE(Настройки!$B$3,3,1),Продажи!$A$2:$A$5000,"<"&DATE(Настройки!$B$3,4,1),Продажи!$F$2:$F$5000,">0") | C7: =SUMIFS(Продажи!$D$2:$D$5000,Продажи!$A$2:$A$5000,">="&DATE(Настройки!$B$3,3,1),Продажи!$A$2:$A$5000,"<"&DATE(Настройки!$B$3,4,1)) | D7: =SUMIFS(Продажи!$F$2:$F$5000,Продажи!$A$2:$A$5000,">="&DATE(Настройки!$B$3,3,1),Продажи!$A$2:$A$5000,"<"&DATE(Настройки!$B$3,4,1)) | E7: =IF(B7=0,0,D7/B7) | F7: =SUMIFS(Расходы!$D$2:$D$5000,Расходы!$A$2:$A$5000,">="&DATE(Настройки!$B$3,3,1),Расходы!$A$2:$A$5000,"<"&DATE(Настройки!$B$3,4,1),Расходы!$B$2:$B$5000,Настройки!$B$8) | G7: =SUMIFS(Расходы!$D$2:$D$5000,Расходы!$A$2:$A$5000,">="&DATE(Настройки!$B$3,3,1),Расходы!$A$2:$A$5000,"<"&DATE(Настройки!$B$3,4,1),Расходы!$B$2:$B$5000,Настройки!$B$9) | H7: =SUMIFS(Расходы!$D$2:$D$5000,Расходы!$A$2:$A$5000,">="&DATE(Настройки!$B$3,3,1),Расходы!$A$2:$A$5000,"<"&DATE(Настройки!$B$3,4,1),Расходы!$B$2:$B$5000,Настройки!$B$10) | I7: =SUMIFS(Расходы!$D$2:$D$5000,Расходы!$A$2:$A$5000,">="&DATE(Настройки!$B$3,3,1),Расходы!$A$2:$A$5000,"<"&DATE(Настройки!$B$3,4,1),Расходы!$B$2:$B$5000,Настройки!$B$11) | J7: =SUMIFS(Расходы!$D$2:$D$5000,Расходы!$A$2:$A$5000,">="&DATE(Настройки!$B$3,3,1),Расходы!$A$2:$A$5000,"<"&DATE(Настройки!$B$3,4,1),Расходы!$B$2:$B$5000,Настройки!$B$12) | K7: =SUMIFS(Расходы!$D$2:$D$5000,Расходы!$A$2:$A$5000,">="&DATE(Настройки!$B$3,3,1),Расходы!$A$2:$A$5000,"<"&DATE(Настройки!$B$3,4,1),Расходы!$B$2:$B$5000,Настройки!$B$13) | L7: =SUMIFS(Расходы!$D$2:$D$5000,Расходы!$A$2:$A$5000,">="&DATE(Настройки!$B$3,3,1),Расходы!$A$2:$A$5000,"<"&DATE(Настройки!$B$3,4,1)) | M7: =D7*Настройки!$B$4 | N7: =D7*Настройки!$B$5 | O7: =D7-L7-M7-N7 | P7: =IF(D7=0,0,O7/D7)
A8: Апрель | B8: =COUNTIFS(Продажи!$A$2:$A$5000,">="&DATE(Настройки!$B$3,4,1),Продажи!$A$2:$A$5000,"<"&DATE(Настройки!$B$3,5,1),Продажи!$F$2:$F$5000,">0") | C8: =SUMIFS(Продажи!$D$2:$D$5000,Продажи!$A$2:$A$5000,">="&DATE(Настройки!$B$3,4,1),Продажи!$A$2:$A$5000,"<"&DATE(Настройки!$B$3,5,1)) | D8: =SUMIFS(Продажи!$F$2:$F$5000,Продажи!$A$2:$A$5000,">="&DATE(Настройки!$B$3,4,1),Продажи!$A$2:$A$5000,"<"&DATE(Настройки!$B$3,5,1)) | E8: =IF(B8=0,0,D8/B8) | F8: =SUMIFS(Расходы!$D$2:$D$5000,Расходы!$A$2:$A$5000,">="&DATE(Настройки!$B$3,4,1),Расходы!$A$2:$A$5000,"<"&DATE(Настройки!$B$3,5,1),Расходы!$B$2:$B$5000,Настройки!$B$8) | G8: =SUMIFS(Расходы!$D$2:$D$5000,Расходы!$A$2:$A$5000,">="&DATE(Настройки!$B$3,4,1),Расходы!$A$2:$A$5000,"<"&DATE(Настройки!$B$3,5,1),Расходы!$B$2:$B$5000,Настройки!$B$9) | H8: =SUMIFS(Расходы!$D$2:$D$5000,Расходы!$A$2:$A$5000,">="&DATE(Настройки!$B$3,4,1),Расходы!$A$2:$A$5000,"<"&DATE(Настройки!$B$3,5,1),Расходы!$B$2:$B$5000,Настройки!$B$10) | I8: =SUMIFS(Расходы!$D$2:$D$5000,Расходы!$A$2:$A$5000,">="&DATE(Настройки!$B$3,4,1),Расходы!$A$2:$A$5000,"<"&DATE(Настройки!$B$3,5,1),Расходы!$B$2:$B$5000,Настройки!$B$11) | J8: =SUMIFS(Расходы!$D$2:$D$5000,Расходы!$A$2:$A$5000,">="&DATE(Настройки!$B$3,4,1),Расходы!$A$2:$A$5000,"<"&DATE(Настройки!$B$3,5,1),Расходы!$B$2:$B$5000,Настройки!$B$12) | K8: =SUMIFS(Расходы!$D$2:$D$5000,Расходы!$A$2:$A$5000,">="&DATE(Настройки!$B$3,4,1),Расходы!$A$2:$A$5000,"<"&DATE(Настройки!$B$3,5,1),Расходы!$B$2:$B$5000,Настройки!$B$13) | L8: =SUMIFS(Расходы!$D$2:$D$5000,Расходы!$A$2:$A$5000,">="&DATE(Настройки!$B$3,4,1),Расходы!$A$2:$A$5000,"<"&DATE(Настройки!$B$3,5,1)) | M8: =D8*Настройки!$B$4 | N8: =D8*Настройки!$B$5 | O8: =D8-L8-M8-N8 | P8: =IF(D8=0,0,O8/D8)
A9: Май | B9: =COUNTIFS(Продажи!$A$2:$A$5000,">="&DATE(Настройки!$B$3,5,1),Продажи!$A$2:$A$5000,"<"&DATE(Настройки!$B$3,6,1),Продажи!$F$2:$F$5000,">0") | C9: =SUMIFS(Продажи!$D$2:$D$5000,Продажи!$A$2:$A$5000,">="&DATE(Настройки!$B$3,5,1),Продажи!$A$2:$A$5000,"<"&DATE(Настройки!$B$3,6,1)) | D9: =SUMIFS(Продажи!$F$2:$F$5000,Продажи!$A$2:$A$5000,">="&DATE(Настройки!$B$3,5,1),Продажи!$A$2:$A$5000,"<"&DATE(Настройки!$B$3,6,1)) | E9: =IF(B9=0,0,D9/B9) | F9: =SUMIFS(Расходы!$D$2:$D$5000,Расходы!$A$2:$A$5000,">="&DATE(Настройки!$B$3,5,1),Расходы!$A$2:$A$5000,"<"&DATE(Настройки!$B$3,6,1),Расходы!$B$2:$B$5000,Настройки!$B$8) | G9: =SUMIFS(Расходы!$D$2:$D$5000,Расходы!$A$2:$A$5000,">="&DATE(Настройки!$B$3,5,1),Расходы!$A$2:$A$5000,"<"&DATE(Настройки!$B$3,6,1),Расходы!$B$2:$B$5000,Настройки!$B$9) | H9: =SUMIFS(Расходы!$D$2:$D$5000,Расходы!$A$2:$A$5000,">="&DATE(Настройки!$B$3,5,1),Расходы!$A$2:$A$5000,"<"&DATE(Настройки!$B$3,6,1),Расходы!$B$2:$B$5000,Настройки!$B$10) | I9: =SUMIFS(Расходы!$D$2:$D$5000,Расходы!$A$2:$A$5000,">="&DATE(Настройки!$B$3,5,1),Расходы!$A$2:$A$5000,"<"&DATE(Настройки!$B$3,6,1),Расходы!$B$2:$B$5000,Настройки!$B$11) | J9: =SUMIFS(Расходы!$D$2:$D$5000,Расходы!$A$2:$A$5000,">="&DATE(Настройки!$B$3,5,1),Расходы!$A$2:$A$5000,"<"&DATE(Настройки!$B$3,6,1),Расходы!$B$2:$B$5000,Настройки!$B$12) | K9: =SUMIFS(Расходы!$D$2:$D$5000,Расходы!$A$2:$A$5000,">="&DATE(Настройки!$B$3,5,1),Расходы!$A$2:$A$5000,"<"&DATE(Настройки!$B$3,6,1),Расходы!$B$2:$B$5000,Настройки!$B$13) | L9: =SUMIFS(Расходы!$D$2:$D$5000,Расходы!$A$2:$A$5000,">="&DATE(Настройки!$B$3,5,1),Расходы!$A$2:$A$5000,"<"&DATE(Настройки!$B$3,6,1)) | M9: =D9*Настройки!$B$4 | N9: =D9*Настройки!$B$5 | O9: =D9-L9-M9-N9 | P9: =IF(D9=0,0,O9/D9)
A10: Июнь | B10: =COUNTIFS(Продажи!$A$2:$A$5000,">="&DATE(Настройки!$B$3,6,1),Продажи!$A$2:$A$5000,"<"&DATE(Настройки!$B$3,7,1),Продажи!$F$2:$F$5000,">0") | C10: =SUMIFS(Продажи!$D$2:$D$5000,Продажи!$A$2:$A$5000,">="&DATE(Настройки!$B$3,6,1),Продажи!$A$2:$A$5000,"<"&DATE(Настройки!$B$3,7,1)) | D10: =SUMIFS(Продажи!$F$2:$F$5000,Продажи!$A$2:$A$5000,">="&DATE(Настройки!$B$3,6,1),Продажи!$A$2:$A$5000,"<"&DATE(Настройки!$B$3,7,1)) | E10: =IF(B10=0,0,D10/B10) | F10: =SUMIFS(Расходы!$D$2:$D$5000,Расходы!$A$2:$A$5000,">="&DATE(Настройки!$B$3,6,1),Расходы!$A$2:$A$5000,"<"&DATE(Настройки!$B$3,7,1),Расходы!$B$2:$B$5000,Настройки!$B$8) | G10: =SUMIFS(Расходы!$D$2:$D$5000,Расходы!$A$2:$A$5000,">="&DATE(Настройки!$B$3,6,1),Расходы!$A$2:$A$5000,"<"&DATE(Настройки!$B$3,7,1),Расходы!$B$2:$B$5000,Настройки!$B$9) | H10: =SUMIFS(Расходы!$D$2:$D$5000,Расходы!$A$2:$A$5000,">="&DATE(Настройки!$B$3,6,1),Расходы!$A$2:$A$5000,"<"&DATE(Настройки!$B$3,7,1),Расходы!$B$2:$B$5000,Настройки!$B$10) | I10: =SUMIFS(Расходы!$D$2:$D$5000,Расходы!$A$2:$A$5000,">="&DATE(Настройки!$B$3,6,1),Расходы!$A$2:$A$5000,"<"&DATE(Настройки!$B$3,7,1),Расходы!$B$2:$B$5000,Настройки!$B$11) | J10: =SUMIFS(Расходы!$D$2:$D$5000,Расходы!$A$2:$A$5000,">="&DATE(Настройки!$B$3,6,1),Расходы!$A$2:$A$5000,"<"&DATE(Настройки!$B$3,7,1),Расходы!$B$2:$B$5000,Настройки!$B$12) | K10: =SUMIFS(Расходы!$D$2:$D$5000,Расходы!$A$2:$A$5000,">="&DATE(Настройки!$B$3,6,1),Расходы!$A$2:$A$5000,"<"&DATE(Настройки!$B$3,7,1),Расходы!$B$2:$B$5000,Настройки!$B$13) | L10: =SUMIFS(Расходы!$D$2:$D$5000,Расходы!$A$2:$A$5000,">="&DATE(Настройки!$B$3,6,1),Расходы!$A$2:$A$5000,"<"&DATE(Настройки!$B$3,7,1)) | M10: =D10*Настройки!$B$4 | N10: =D10*Настройки!$B$5 | O10: =D10-L10-M10-N10 | P10: =IF(D10=0,0,O10/D10)
A11: Июль | B11: =COUNTIFS(Продажи!$A$2:$A$5000,">="&DATE(Настройки!$B$3,7,1),Продажи!$A$2:$A$5000,"<"&DATE(Настройки!$B$3,8,1),Продажи!$F$2:$F$5000,">0") | C11: =SUMIFS(Продажи!$D$2:$D$5000,Продажи!$A$2:$A$5000,">="&DATE(Настройки!$B$3,7,1),Продажи!$A$2:$A$5000,"<"&DATE(Настройки!$B$3,8,1)) | D11: =SUMIFS(Продажи!$F$2:$F$5000,Продажи!$A$2:$A$5000,">="&DATE(Настройки!$B$3,7,1),Продажи!$A$2:$A$5000,"<"&DATE(Настройки!$B$3,8,1)) | E11: =IF(B11=0,0,D11/B11) | F11: =SUMIFS(Расходы!$D$2:$D$5000,Расходы!$A$2:$A$5000,">="&DATE(Настройки!$B$3,7,1),Расходы!$A$2:$A$5000,"<"&DATE(Настройки!$B$3,8,1),Расходы!$B$2:$B$5000,Настройки!$B$8) | G11: =SUMIFS(Расходы!$D$2:$D$5000,Расходы!$A$2:$A$5000,">="&DATE(Настройки!$B$3,7,1),Расходы!$A$2:$A$5000,"<"&DATE(Настройки!$B$3,8,1),Расходы!$B$2:$B$5000,Настройки!$B$9) | H11: =SUMIFS(Расходы!$D$2:$D$5000,Расходы!$A$2:$A$5000,">="&DATE(Настройки!$B$3,7,1),Расходы!$A$2:$A$5000,"<"&DATE(Настройки!$B$3,8,1),Расходы!$B$2:$B$5000,Настройки!$B$10) | I11: =SUMIFS(Расходы!$D$2:$D$5000,Расходы!$A$2:$A$5000,">="&DATE(Настройки!$B$3,7,1),Расходы!$A$2:$A$5000,"<"&DATE(Настройки!$B$3,8,1),Расходы!$B$2:$B$5000,Настройки!$B$11) | J11: =SUMIFS(Расходы!$D$2:$D$5000,Расходы!$A$2:$A$5000,">="&DATE(Настройки!$B$3,7,1),Расходы!$A$2:$A$5000,"<"&DATE(Настройки!$B$3,8,1),Расходы!$B$2:$B$5000,Настройки!$B$12) | K11: =SUMIFS(Расходы!$D$2:$D$5000,Расходы!$A$2:$A$5000,">="&DATE(Настройки!$B$3,7,1),Расходы!$A$2:$A$5000,"<"&DATE(Настройки!$B$3,8,1),Расходы!$B$2:$B$5000,Настройки!$B$13) | L11: =SUMIFS(Расходы!$D$2:$D$5000,Расходы!$A$2:$A$5000,">="&DATE(Настройки!$B$3,7,1),Расходы!$A$2:$A$5000,"<"&DATE(Настройки!$B$3,8,1)) | M11: =D11*Настройки!$B$4 | N11: =D11*Настройки!$B$5 | O11: =D11-L11-M11-N11 | P11: =IF(D11=0,0,O11/D11)
A12: Август | B12: =COUNTIFS(Продажи!$A$2:$A$5000,">="&DATE(Настройки!$B$3,8,1),Продажи!$A$2:$A$5000,"<"&DATE(Настройки!$B$3,9,1),Продажи!$F$2:$F$5000,">0") | C12: =SUMIFS(Продажи!$D$2:$D$5000,Продажи!$A$2:$A$5000,">="&DATE(Настройки!$B$3,8,1),Продажи!$A$2:$A$5000,"<"&DATE(Настройки!$B$3,9,1)) | D12: =SUMIFS(Продажи!$F$2:$F$5000,Продажи!$A$2:$A$5000,">="&DATE(Настройки!$B$3,8,1),Продажи!$A$2:$A$5000,"<"&DATE(Настройки!$B$3,9,1)) | E12: =IF(B12=0,0,D12/B12) | F12: =SUMIFS(Расходы!$D$2:$D$5000,Расходы!$A$2:$A$5000,">="&DATE(Настройки!$B$3,8,1),Расходы!$A$2:$A$5000,"<"&DATE(Настройки!$B$3,9,1),Расходы!$B$2:$B$5000,Настройки!$B$8) | G12: =SUMIFS(Расходы!$D$2:$D$5000,Расходы!$A$2:$A$5000,">="&DATE(Настройки!$B$3,8,1),Расходы!$A$2:$A$5000,"<"&DATE(Настройки!$B$3,9,1),Расходы!$B$2:$B$5000,Настройки!$B$9) | H12: =SUMIFS(Расходы!$D$2:$D$5000,Расходы!$A$2:$A$5000,">="&DATE(Настройки!$B$3,8,1),Расходы!$A$2:$A$5000,"<"&DATE(Настройки!$B$3,9,1),Расходы!$B$2:$B$5000,Настройки!$B$10) | I12: =SUMIFS(Расходы!$D$2:$D$5000,Расходы!$A$2:$A$5000,">="&DATE(Настройки!$B$3,8,1),Расходы!$A$2:$A$5000,"<"&DATE(Настройки!$B$3,9,1),Расходы!$B$2:$B$5000,Настройки!$B$11) | J12: =SUMIFS(Расходы!$D$2:$D$5000,Расходы!$A$2:$A$5000,">="&DATE(Настройки!$B$3,8,1),Расходы!$A$2:$A$5000,"<"&DATE(Настройки!$B$3,9,1),Расходы!$B$2:$B$5000,Настройки!$B$12) | K12: =SUMIFS(Расходы!$D$2:$D$5000,Расходы!$A$2:$A$5000,">="&DATE(Настройки!$B$3,8,1),Расходы!$A$2:$A$5000,"<"&DATE(Настройки!$B$3,9,1),Расходы!$B$2:$B$5000,Настройки!$B$13) | L12: =SUMIFS(Расходы!$D$2:$D$5000,Расходы!$A$2:$A$5000,">="&DATE(Настройки!$B$3,8,1),Расходы!$A$2:$A$5000,"<"&DATE(Настройки!$B$3,9,1)) | M12: =D12*Настройки!$B$4 | N12: =D12*Настройки!$B$5 | O12: =D12-L12-M12-N12 | P12: =IF(D12=0,0,O12/D12)
A13: Сентябрь | B13: =COUNTIFS(Продажи!$A$2:$A$5000,">="&DATE(Настройки!$B$3,9,1),Продажи!$A$2:$A$5000,"<"&DATE(Настройки!$B$3,10,1),Продажи!$F$2:$F$5000,">0") | C13: =SUMIFS(Продажи!$D$2:$D$5000,Продажи!$A$2:$A$5000,">="&DATE(Настройки!$B$3,9,1),Продажи!$A$2:$A$5000,"<"&DATE(Настройки!$B$3,10,1)) | D13: =SUMIFS(Продажи!$F$2:$F$5000,Продажи!$A$2:$A$5000,">="&DATE(Настройки!$B$3,9,1),Продажи!$A$2:$A$5000,"<"&DATE(Настройки!$B$3,10,1)) | E13: =IF(B13=0,0,D13/B13) | F13: =SUMIFS(Расходы!$D$2:$D$5000,Расходы!$A$2:$A$5000,">="&DATE(Настройки!$B$3,9,1),Расходы!$A$2:$A$5000,"<"&DATE(Настройки!$B$3,10,1),Расходы!$B$2:$B$5000,Настройки!$B$8) | G13: =SUMIFS(Расходы!$D$2:$D$5000,Расходы!$A$2:$A$5000,">="&DATE(Настройки!$B$3,9,1),Расходы!$A$2:$A$5000,"<"&DATE(Настройки!$B$3,10,1),Расходы!$B$2:$B$5000,Настройки!$B$9) | H13: =SUMIFS(Расходы!$D$2:$D$5000,Расходы!$A$2:$A$5000,">="&DATE(Настройки!$B$3,9,1),Расходы!$A$2:$A$5000,"<"&DATE(Настройки!$B$3,10,1),Расходы!$B$2:$B$5000,Настройки!$B$10) | I13: =SUMIFS(Расходы!$D$2:$D$5000,Расходы!$A$2:$A$5000,">="&DATE(Настройки!$B$3,9,1),Расходы!$A$2:$A$5000,"<"&DATE(Настройки!$B$3,10,1),Расходы!$B$2:$B$5000,Настройки!$B$11) | J13: =SUMIFS(Расходы!$D$2:$D$5000,Расходы!$A$2:$A$5000,">="&DATE(Настройки!$B$3,9,1),Расходы!$A$2:$A$5000,"<"&DATE(Настройки!$B$3,10,1),Расходы!$B$2:$B$5000,Настройки!$B$12) | K13: =SUMIFS(Расходы!$D$2:$D$5000,Расходы!$A$2:$A$5000,">="&DATE(Настройки!$B$3,9,1),Расходы!$A$2:$A$5000,"<"&DATE(Настройки!$B$3,10,1),Расходы!$B$2:$B$5000,Настройки!$B$13) | L13: =SUMIFS(Расходы!$D$2:$D$5000,Расходы!$A$2:$A$5000,">="&DATE(Настройки!$B$3,9,1),Расходы!$A$2:$A$5000,"<"&DATE(Настройки!$B$3,10,1)) | M13: =D13*Настройки!$B$4 | N13: =D13*Настройки!$B$5 | O13: =D13-L13-M13-N13 | P13: =IF(D13=0,0,O13/D13)
A14: Октябрь | B14: =COUNTIFS(Продажи!$A$2:$A$5000,">="&DATE(Настройки!$B$3,10,1),Продажи!$A$2:$A$5000,"<"&DATE(Настройки!$B$3,11,1),Продажи!$F$2:$F$5000,">0") | C14: =SUMIFS(Продажи!$D$2:$D$5000,Продажи!$A$2:$A$5000,">="&DATE(Настройки!$B$3,10,1),Продажи!$A$2:$A$5000,"<"&DATE(Настройки!$B$3,11,1)) | D14: =SUMIFS(Продажи!$F$2:$F$5000,Продажи!$A$2:$A$5000,">="&DATE(Настройки!$B$3,10,1),Продажи!$A$2:$A$5000,"<"&DATE(Настройки!$B$3,11,1)) | E14: =IF(B14=0,0,D14/B14) | F14: =SUMIFS(Расходы!$D$2:$D$5000,Расходы!$A$2:$A$5000,">="&DATE(Настройки!$B$3,10,1),Расходы!$A$2:$A$5000,"<"&DATE(Настройки!$B$3,11,1),Расходы!$B$2:$B$5000,Настройки!$B$8) | G14: =SUMIFS(Расходы!$D$2:$D$5000,Расходы!$A$2:$A$5000,">="&DATE(Настройки!$B$3,10,1),Расходы!$A$2:$A$5000,"<"&DATE(Настройки!$B$3,11,1),Расходы!$B$2:$B$5000,Настройки!$B$9) | H14: =SUMIFS(Расходы!$D$2:$D$5000,Расходы!$A$2:$A$5000,">="&DATE(Настройки!$B$3,10,1),Расходы!$A$2:$A$5000,"<"&DATE(Настройки!$B$3,11,1),Расходы!$B$2:$B$5000,Настройки!$B$10) | I14: =SUMIFS(Расходы!$D$2:$D$5000,Расходы!$A$2:$A$5000,">="&DATE(Настройки!$B$3,10,1),Расходы!$A$2:$A$5000,"<"&DATE(Настройки!$B$3,11,1),Расходы!$B$2:$B$5000,Настройки!$B$11) | J14: =SUMIFS(Расходы!$D$2:$D$5000,Расходы!$A$2:$A$5000,">="&DATE(Настройки!$B$3,10,1),Расходы!$A$2:$A$5000,"<"&DATE(Настройки!$B$3,11,1),Расходы!$B$2:$B$5000,Настройки!$B$12) | K14: =SUMIFS(Расходы!$D$2:$D$5000,Расходы!$A$2:$A$5000,">="&DATE(Настройки!$B$3,10,1),Расходы!$A$2:$A$5000,"<"&DATE(Настройки!$B$3,11,1),Расходы!$B$2:$B$5000,Настройки!$B$13) | L14: =SUMIFS(Расходы!$D$2:$D$5000,Расходы!$A$2:$A$5000,">="&DATE(Настройки!$B$3,10,1),Расходы!$A$2:$A$5000,"<"&DATE(Настройки!$B$3,11,1)) | M14: =D14*Настройки!$B$4 | N14: =D14*Настройки!$B$5 | O14: =D14-L14-M14-N14 | P14: =IF(D14=0,0,O14/D14)
A15: Ноябрь | B15: =COUNTIFS(Продажи!$A$2:$A$5000,">="&DATE(Настройки!$B$3,11,1),Продажи!$A$2:$A$5000,"<"&DATE(Настройки!$B$3,12,1),Продажи!$F$2:$F$5000,">0") | C15: =SUMIFS(Продажи!$D$2:$D$5000,Продажи!$A$2:$A$5000,">="&DATE(Настройки!$B$3,11,1),Продажи!$A$2:$A$5000,"<"&DATE(Настройки!$B$3,12,1)) | D15: =SUMIFS(Продажи!$F$2:$F$5000,Продажи!$A$2:$A$5000,">="&DATE(Настройки!$B$3,11,1),Продажи!$A$2:$A$5000,"<"&DATE(Настройки!$B$3,12,1)) | E15: =IF(B15=0,0,D15/B15) | F15: =SUMIFS(Расходы!$D$2:$D$5000,Расходы!$A$2:$A$5000,">="&DATE(Настройки!$B$3,11,1),Расходы!$A$2:$A$5000,"<"&DATE(Настройки!$B$3,12,1),Расходы!$B$2:$B$5000,Настройки!$B$8) | G15: =SUMIFS(Расходы!$D$2:$D$5000,Расходы!$A$2:$A$5000,">="&DATE(Настройки!$B$3,11,1),Расходы!$A$2:$A$5000,"<"&DATE(Настройки!$B$3,12,1),Расходы!$B$2:$B$5000,Настройки!$B$9) | H15: =SUMIFS(Расходы!$D$2:$D$5000,Расходы!$A$2:$A$5000,">="&DATE(Настройки!$B$3,11,1),Расходы!$A$2:$A$5000,"<"&DATE(Настройки!$B$3,12,1),Расходы!$B$2:$B$5000,Настройки!$B$10) | I15: =SUMIFS(Расходы!$D$2:$D$5000,Расходы!$A$2:$A$5000,">="&DATE(Настройки!$B$3,11,1),Расходы!$A$2:$A$5000,"<"&DATE(Настройки!$B$3,12,1),Расходы!$B$2:$B$5000,Настройки!$B$11) | J15: =SUMIFS(Расходы!$D$2:$D$5000,Расходы!$A$2:$A$5000,">="&DATE(Настройки!$B$3,11,1),Расходы!$A$2:$A$5000,"<"&DATE(Настройки!$B$3,12,1),Расходы!$B$2:$B$5000,Настройки!$B$12) | K15: =SUMIFS(Расходы!$D$2:$D$5000,Расходы!$A$2:$A$5000,">="&DATE(Настройки!$B$3,11,1),Расходы!$A$2:$A$5000,"<"&DATE(Настройки!$B$3,12,1),Расходы!$B$2:$B$5000,Настройки!$B$13) | L15: =SUMIFS(Расходы!$D$2:$D$5000,Расходы!$A$2:$A$5000,">="&DATE(Настройки!$B$3,11,1),Расходы!$A$2:$A$5000,"<"&DATE(Настройки!$B$3,12,1)) | M15: =D15*Настройки!$B$4 | N15: =D15*Настройки!$B$5 | O15: =D15-L15-M15-N15 | P15: =IF(D15=0,0,O15/D15)
A16: Декабрь | B16: =COUNTIFS(Продажи!$A$2:$A$5000,">="&DATE(Настройки!$B$3,12,1),Продажи!$A$2:$A$5000,"<"&DATE(Настройки!$B$3,13,1),Продажи!$F$2:$F$5000,">0") | C16: =SUMIFS(Продажи!$D$2:$D$5000,Продажи!$A$2:$A$5000,">="&DATE(Настройки!$B$3,12,1),Продажи!$A$2:$A$5000,"<"&DATE(Настройки!$B$3,13,1)) | D16: =SUMIFS(Продажи!$F$2:$F$5000,Продажи!$A$2:$A$5000,">="&DATE(Настройки!$B$3,12,1),Продажи!$A$2:$A$5000,"<"&DATE(Настройки!$B$3,13,1)) | E16: =IF(B16=0,0,D16/B16) | F16: =SUMIFS(Расходы!$D$2:$D$5000,Расходы!$A$2:$A$5000,">="&DATE(Настройки!$B$3,12,1),Расходы!$A$2:$A$5000,"<"&DATE(Настройки!$B$3,13,1),Расходы!$B$2:$B$5000,Настройки!$B$8) | G16: =SUMIFS(Расходы!$D$2:$D$5000,Расходы!$A$2:$A$5000,">="&DATE(Настройки!$B$3,12,1),Расходы!$A$2:$A$5000,"<"&DATE(Настройки!$B$3,13,1),Расходы!$B$2:$B$5000,Настройки!$B$9) | H16: =SUMIFS(Расходы!$D$2:$D$5000,Расходы!$A$2:$A$5000,">="&DATE(Настройки!$B$3,12,1),Расходы!$A$2:$A$5000,"<"&DATE(Настройки!$B$3,13,1),Расходы!$B$2:$B$5000,Настройки!$B$10) | I16: =SUMIFS(Расходы!$D$2:$D$5000,Расходы!$A$2:$A$5000,">="&DATE(Настройки!$B$3,12,1),Расходы!$A$2:$A$5000,"<"&DATE(Настройки!$B$3,13,1),Расходы!$B$2:$B$5000,Настройки!$B$11) | J16: =SUMIFS(Расходы!$D$2:$D$5000,Расходы!$A$2:$A$5000,">="&DATE(Настройки!$B$3,12,1),Расходы!$A$2:$A$5000,"<"&DATE(Настройки!$B$3,13,1),Расходы!$B$2:$B$5000,Настройки!$B$12) | K16: =SUMIFS(Расходы!$D$2:$D$5000,Расходы!$A$2:$A$5000,">="&DATE(Настройки!$B$3,12,1),Расходы!$A$2:$A$5000,"<"&DATE(Настройки!$B$3,13,1),Расходы!$B$2:$B$5000,Настройки!$B$13) | L16: =SUMIFS(Расходы!$D$2:$D$5000,Расходы!$A$2:$A$5000,">="&DATE(Настройки!$B$3,12,1),Расходы!$A$2:$A$5000,"<"&DATE(Настройки!$B$3,13,1)) | M16: =D16*Настройки!$B$4 | N16: =D16*Настройки!$B$5 | O16: =D16-L16-M16-N16 | P16: =IF(D16=0,0,O16/D16)
A17: ГОД | B17: =COUNTIFS(Продажи!$A$2:$A$5000,">="&DATE(Настройки!$B$3,1,1),Продажи!$A$2:$A$5000,"<"&DATE(Настройки!$B$3+1,1,1),Продажи!$F$2:$F$5000,">0") | C17: =SUMIFS(Продажи!$D$2:$D$5000,Продажи!$A$2:$A$5000,">="&DATE(Настройки!$B$3,1,1),Продажи!$A$2:$A$5000,"<"&DATE(Настройки!$B$3+1,1,1)) | D17: =SUMIFS(Продажи!$F$2:$F$5000,Продажи!$A$2:$A$5000,">="&DATE(Настройки!$B$3,1,1),Продажи!$A$2:$A$5000,"<"&DATE(Настройки!$B$3+1,1,1)) | E17: =IF(B17=0,0,D17/B17) | F17: =SUMIFS(Расходы!$D$2:$D$5000,Расходы!$A$2:$A$5000,">="&DATE(Настройки!$B$3,1,1),Расходы!$A$2:$A$5000,"<"&DATE(Настройки!$B$3+1,1,1),Расходы!$B$2:$B$5000,Настройки!$B$8) | G17: =SUMIFS(Расходы!$D$2:$D$5000,Расходы!$A$2:$A$5000,">="&DATE(Настройки!$B$3,1,1),Расходы!$A$2:$A$5000,"<"&DATE(Настройки!$B$3+1,1,1),Расходы!$B$2:$B$5000,Настройки!$B$9) | H17: =SUMIFS(Расходы!$D$2:$D$5000,Расходы!$A$2:$A$5000,">="&DATE(Настройки!$B$3,1,1),Расходы!$A$2:$A$5000,"<"&DATE(Настройки!$B$3+1,1,1),Расходы!$B$2:$B$5000,Настройки!$B$10) | I17: =SUMIFS(Расходы!$D$2:$D$5000,Расходы!$A$2:$A$5000,">="&DATE(Настройки!$B$3,1,1),Расходы!$A$2:$A$5000,"<"&DATE(Настройки!$B$3+1,1,1),Расходы!$B$2:$B$5000,Настройки!$B$11) | J17: =SUMIFS(Расходы!$D$2:$D$5000,Расходы!$A$2:$A$5000,">="&DATE(Настройки!$B$3,1,1),Расходы!$A$2:$A$5000,"<"&DATE(Настройки!$B$3+1,1,1),Расходы!$B$2:$B$5000,Настройки!$B$12) | K17: =SUMIFS(Расходы!$D$2:$D$5000,Расходы!$A$2:$A$5000,">="&DATE(Настройки!$B$3,1,1),Расходы!$A$2:$A$5000,"<"&DATE(Настройки!$B$3+1,1,1),Расходы!$B$2:$B$5000,Настройки!$B$13) | L17: =SUMIFS(Расходы!$D$2:$D$5000,Расходы!$A$2:$A$5000,">="&DATE(Настройки!$B$3,1,1),Расходы!$A$2:$A$5000,"<"&DATE(Настройки!$B$3+1,1,1)) | M17: =D17*Настройки!$B$4 | N17: =D17*Настройки!$B$5 | O17: =D17-L17-M17-N17 | P17: =IF(D17=0,0,O17/D17)
A19: Период | B19: Заказов | C19: Поздравлений, шт | D19: Выручка, $ | E19: Средний чек, $ | F19: Реклама / продвижение | G19: Подрядчики / монтаж | H19: Сервисы и подписки | I19: Оборудование | J19: Комиссии банка | K19: Прочее | L19: Расходы итого, $ | M19: Налог, $ | N19: Комиссия, $ | O19: Чистая прибыль, $ | P19: Маржа, %
A20: 1 квартал | B20: =COUNTIFS(Продажи!$A$2:$A$5000,">="&DATE(Настройки!$B$3,1,1),Продажи!$A$2:$A$5000,"<"&DATE(Настройки!$B$3,4,1),Продажи!$F$2:$F$5000,">0") | C20: =SUMIFS(Продажи!$D$2:$D$5000,Продажи!$A$2:$A$5000,">="&DATE(Настройки!$B$3,1,1),Продажи!$A$2:$A$5000,"<"&DATE(Настройки!$B$3,4,1)) | D20: =SUMIFS(Продажи!$F$2:$F$5000,Продажи!$A$2:$A$5000,">="&DATE(Настройки!$B$3,1,1),Продажи!$A$2:$A$5000,"<"&DATE(Настройки!$B$3,4,1)) | E20: =IF(B20=0,0,D20/B20) | F20: =SUMIFS(Расходы!$D$2:$D$5000,Расходы!$A$2:$A$5000,">="&DATE(Настройки!$B$3,1,1),Расходы!$A$2:$A$5000,"<"&DATE(Настройки!$B$3,4,1),Расходы!$B$2:$B$5000,Настройки!$B$8) | G20: =SUMIFS(Расходы!$D$2:$D$5000,Расходы!$A$2:$A$5000,">="&DATE(Настройки!$B$3,1,1),Расходы!$A$2:$A$5000,"<"&DATE(Настройки!$B$3,4,1),Расходы!$B$2:$B$5000,Настройки!$B$9) | H20: =SUMIFS(Расходы!$D$2:$D$5000,Расходы!$A$2:$A$5000,">="&DATE(Настройки!$B$3,1,1),Расходы!$A$2:$A$5000,"<"&DATE(Настройки!$B$3,4,1),Расходы!$B$2:$B$5000,Настройки!$B$10) | I20: =SUMIFS(Расходы!$D$2:$D$5000,Расходы!$A$2:$A$5000,">="&DATE(Настройки!$B$3,1,1),Расходы!$A$2:$A$5000,"<"&DATE(Настройки!$B$3,4,1),Расходы!$B$2:$B$5000,Настройки!$B$11) | J20: =SUMIFS(Расходы!$D$2:$D$5000,Расходы!$A$2:$A$5000,">="&DATE(Настройки!$B$3,1,1),Расходы!$A$2:$A$5000,"<"&DATE(Настройки!$B$3,4,1),Расходы!$B$2:$B$5000,Настройки!$B$12) | K20: =SUMIFS(Расходы!$D$2:$D$5000,Расходы!$A$2:$A$5000,">="&DATE(Настройки!$B$3,1,1),Расходы!$A$2:$A$5000,"<"&DATE(Настройки!$B$3,4,1),Расходы!$B$2:$B$5000,Настройки!$B$13) | L20: =SUMIFS(Расходы!$D$2:$D$5000,Расходы!$A$2:$A$5000,">="&DATE(Настройки!$B$3,1,1),Расходы!$A$2:$A$5000,"<"&DATE(Настройки!$B$3,4,1)) | M20: =D20*Настройки!$B$4 | N20: =D20*Настройки!$B$5 | O20: =D20-L20-M20-N20 | P20: =IF(D20=0,0,O20/D20)
A21: 2 квартал | B21: =COUNTIFS(Продажи!$A$2:$A$5000,">="&DATE(Настройки!$B$3,4,1),Продажи!$A$2:$A$5000,"<"&DATE(Настройки!$B$3,7,1),Продажи!$F$2:$F$5000,">0") | C21: =SUMIFS(Продажи!$D$2:$D$5000,Продажи!$A$2:$A$5000,">="&DATE(Настройки!$B$3,4,1),Продажи!$A$2:$A$5000,"<"&DATE(Настройки!$B$3,7,1)) | D21: =SUMIFS(Продажи!$F$2:$F$5000,Продажи!$A$2:$A$5000,">="&DATE(Настройки!$B$3,4,1),Продажи!$A$2:$A$5000,"<"&DATE(Настройки!$B$3,7,1)) | E21: =IF(B21=0,0,D21/B21) | F21: =SUMIFS(Расходы!$D$2:$D$5000,Расходы!$A$2:$A$5000,">="&DATE(Настройки!$B$3,4,1),Расходы!$A$2:$A$5000,"<"&DATE(Настройки!$B$3,7,1),Расходы!$B$2:$B$5000,Настройки!$B$8) | G21: =SUMIFS(Расходы!$D$2:$D$5000,Расходы!$A$2:$A$5000,">="&DATE(Настройки!$B$3,4,1),Расходы!$A$2:$A$5000,"<"&DATE(Настройки!$B$3,7,1),Расходы!$B$2:$B$5000,Настройки!$B$9) | H21: =SUMIFS(Расходы!$D$2:$D$5000,Расходы!$A$2:$A$5000,">="&DATE(Настройки!$B$3,4,1),Расходы!$A$2:$A$5000,"<"&DATE(Настройки!$B$3,7,1),Расходы!$B$2:$B$5000,Настройки!$B$10) | I21: =SUMIFS(Расходы!$D$2:$D$5000,Расходы!$A$2:$A$5000,">="&DATE(Настройки!$B$3,4,1),Расходы!$A$2:$A$5000,"<"&DATE(Настройки!$B$3,7,1),Расходы!$B$2:$B$5000,Настройки!$B$11) | J21: =SUMIFS(Расходы!$D$2:$D$5000,Расходы!$A$2:$A$5000,">="&DATE(Настройки!$B$3,4,1),Расходы!$A$2:$A$5000,"<"&DATE(Настройки!$B$3,7,1),Расходы!$B$2:$B$5000,Настройки!$B$12) | K21: =SUMIFS(Расходы!$D$2:$D$5000,Расходы!$A$2:$A$5000,">="&DATE(Настройки!$B$3,4,1),Расходы!$A$2:$A$5000,"<"&DATE(Настройки!$B$3,7,1),Расходы!$B$2:$B$5000,Настройки!$B$13) | L21: =SUMIFS(Расходы!$D$2:$D$5000,Расходы!$A$2:$A$5000,">="&DATE(Настройки!$B$3,4,1),Расходы!$A$2:$A$5000,"<"&DATE(Настройки!$B$3,7,1)) | M21: =D21*Настройки!$B$4 | N21: =D21*Настройки!$B$5 | O21: =D21-L21-M21-N21 | P21: =IF(D21=0,0,O21/D21)
A22: 3 квартал | B22: =COUNTIFS(Продажи!$A$2:$A$5000,">="&DATE(Настройки!$B$3,7,1),Продажи!$A$2:$A$5000,"<"&DATE(Настройки!$B$3,10,1),Продажи!$F$2:$F$5000,">0") | C22: =SUMIFS(Продажи!$D$2:$D$5000,Продажи!$A$2:$A$5000,">="&DATE(Настройки!$B$3,7,1),Продажи!$A$2:$A$5000,"<"&DATE(Настройки!$B$3,10,1)) | D22: =SUMIFS(Продажи!$F$2:$F$5000,Продажи!$A$2:$A$5000,">="&DATE(Настройки!$B$3,7,1),Продажи!$A$2:$A$5000,"<"&DATE(Настройки!$B$3,10,1)) | E22: =IF(B22=0,0,D22/B22) | F22: =SUMIFS(Расходы!$D$2:$D$5000,Расходы!$A$2:$A$5000,">="&DATE(Настройки!$B$3,7,1),Расходы!$A$2:$A$5000,"<"&DATE(Настройки!$B$3,10,1),Расходы!$B$2:$B$5000,Настройки!$B$8) | G22: =SUMIFS(Расходы!$D$2:$D$5000,Расходы!$A$2:$A$5000,">="&DATE(Настройки!$B$3,7,1),Расходы!$A$2:$A$5000,"<"&DATE(Настройки!$B$3,10,1),Расходы!$B$2:$B$5000,Настройки!$B$9) | H22: =SUMIFS(Расходы!$D$2:$D$5000,Расходы!$A$2:$A$5000,">="&DATE(Настройки!$B$3,7,1),Расходы!$A$2:$A$5000,"<"&DATE(Настройки!$B$3,10,1),Расходы!$B$2:$B$5000,Настройки!$B$10) | I22: =SUMIFS(Расходы!$D$2:$D$5000,Расходы!$A$2:$A$5000,">="&DATE(Настройки!$B$3,7,1),Расходы!$A$2:$A$5000,"<"&DATE(Настройки!$B$3,10,1),Расходы!$B$2:$B$5000,Настройки!$B$11) | J22: =SUMIFS(Расходы!$D$2:$D$5000,Расходы!$A$2:$A$5000,">="&DATE(Настройки!$B$3,7,1),Расходы!$A$2:$A$5000,"<"&DATE(Настройки!$B$3,10,1),Расходы!$B$2:$B$5000,Настройки!$B$12) | K22: =SUMIFS(Расходы!$D$2:$D$5000,Расходы!$A$2:$A$5000,">="&DATE(Настройки!$B$3,7,1),Расходы!$A$2:$A$5000,"<"&DATE(Настройки!$B$3,10,1),Расходы!$B$2:$B$5000,Настройки!$B$13) | L22: =SUMIFS(Расходы!$D$2:$D$5000,Расходы!$A$2:$A$5000,">="&DATE(Настройки!$B$3,7,1),Расходы!$A$2:$A$5000,"<"&DATE(Настройки!$B$3,10,1)) | M22: =D22*Настройки!$B$4 | N22: =D22*Настройки!$B$5 | O22: =D22-L22-M22-N22 | P22: =IF(D22=0,0,O22/D22)
A23: 4 квартал | B23: =COUNTIFS(Продажи!$A$2:$A$5000,">="&DATE(Настройки!$B$3,10,1),Продажи!$A$2:$A$5000,"<"&DATE(Настройки!$B$3,13,1),Продажи!$F$2:$F$5000,">0") | C23: =SUMIFS(Продажи!$D$2:$D$5000,Продажи!$A$2:$A$5000,">="&DATE(Настройки!$B$3,10,1),Продажи!$A$2:$A$5000,"<"&DATE(Настройки!$B$3,13,1)) | D23: =SUMIFS(Продажи!$F$2:$F$5000,Продажи!$A$2:$A$5000,">="&DATE(Настройки!$B$3,10,1),Продажи!$A$2:$A$5000,"<"&DATE(Настройки!$B$3,13,1)) | E23: =IF(B23=0,0,D23/B23) | F23: =SUMIFS(Расходы!$D$2:$D$5000,Расходы!$A$2:$A$5000,">="&DATE(Настройки!$B$3,10,1),Расходы!$A$2:$A$5000,"<"&DATE(Настройки!$B$3,13,1),Расходы!$B$2:$B$5000,Настройки!$B$8) | G23: =SUMIFS(Расходы!$D$2:$D$5000,Расходы!$A$2:$A$5000,">="&DATE(Настройки!$B$3,10,1),Расходы!$A$2:$A$5000,"<"&DATE(Настройки!$B$3,13,1),Расходы!$B$2:$B$5000,Настройки!$B$9) | H23: =SUMIFS(Расходы!$D$2:$D$5000,Расходы!$A$2:$A$5000,">="&DATE(Настройки!$B$3,10,1),Расходы!$A$2:$A$5000,"<"&DATE(Настройки!$B$3,13,1),Расходы!$B$2:$B$5000,Настройки!$B$10) | I23: =SUMIFS(Расходы!$D$2:$D$5000,Расходы!$A$2:$A$5000,">="&DATE(Настройки!$B$3,10,1),Расходы!$A$2:$A$5000,"<"&DATE(Настройки!$B$3,13,1),Расходы!$B$2:$B$5000,Настройки!$B$11) | J23: =SUMIFS(Расходы!$D$2:$D$5000,Расходы!$A$2:$A$5000,">="&DATE(Настройки!$B$3,10,1),Расходы!$A$2:$A$5000,"<"&DATE(Настройки!$B$3,13,1),Расходы!$B$2:$B$5000,Настройки!$B$12) | K23: =SUMIFS(Расходы!$D$2:$D$5000,Расходы!$A$2:$A$5000,">="&DATE(Настройки!$B$3,10,1),Расходы!$A$2:$A$5000,"<"&DATE(Настройки!$B$3,13,1),Расходы!$B$2:$B$5000,Настройки!$B$13) | L23: =SUMIFS(Расходы!$D$2:$D$5000,Расходы!$A$2:$A$5000,">="&DATE(Настройки!$B$3,10,1),Расходы!$A$2:$A$5000,"<"&DATE(Настройки!$B$3,13,1)) | M23: =D23*Настройки!$B$4 | N23: =D23*Настройки!$B$5 | O23: =D23-L23-M23-N23 | P23: =IF(D23=0,0,O23/D23)
A25: Новые категории расходов, добавленные в Настройки, учитываются в «Расходы итого».

Sheet Настройки
A1: Настройки
A3: Год отчёта | B3: 2026
A4: Налог, % от выручки | B4: 0.05
A5: Комиссия платёжки, % от выручки | B5: 0
A7: Виды поздравлений | B7: Категории расходов | D7: Списки можно дополнять (до строки 30) — они появятся в выпадающих меню.
A8: Видео-поздравление | B8: Реклама / продвижение
A9: Голосовое | B9: Подрядчики / монтаж
A10: Текстовое | B10: Сервисы и подписки
A11: Срочное | B11: Оборудование
A12: Другое | B12: Комиссии банка
B13: Прочее

Sheet Продажи
A1: Дата | B1: Клиент / ник | C1: Вид поздравления | D1: Кол-во | E1: Цена за 1, $ | F1: Сумма, $ | G1: Способ оплаты | H1: Комментарий
A2: 46027 | B2: @anna | C2: Видео-поздравление | D2: 1 | E2: 15 | F2: =IF(OR(D2="",E2=""),"",D2*E2)
A3: 46034 | B3: @oleg | C3: Голосовое | D3: 2 | E3: 20 | F3: =IF(OR(D3="",E3=""),"",D3*E3)
A4: 46056 | B4: @kate | C4: Видео-поздравление | D4: 1 | E4: 30 | F4: =IF(OR(D4="",E4=""),"",D4*E4)
F5: =IF(OR(D5="",E5=""),"",D5*E5)
F6: =IF(OR(D6="",E6=""),"",D6*E6)
F7: =IF(OR(D7="",E7=""),"",D7*E7)
F8: =IF(OR(D8="",E8=""),"",D8*E8)
F9: =IF(OR(D9="",E9=""),"",D9*E9)
F10: =IF(OR(D10="",E10=""),"",D10*E10)
F11: =IF(OR(D11="",E11=""),"",D11*E11)
F12: =IF(OR(D12="",E12=""),"",D12*E12)
F13: =IF(OR(D13="",E13=""),"",D13*E13)
F14: =IF(OR(D14="",E14=""),"",D14*E14)
F15: =IF(OR(D15="",E15=""),"",D15*E15)
F16: =IF(OR(D16="",E16=""),"",D16*E16)
... F5000: =IF(OR(D5000="",E5000=""),"",D5000*E5000)

Sheet Расходы
A1: Дата | B1: Категория | C1: Описание | D1: Сумма, $
A2: 46032 | B2: Реклама / продвижение | C2: Таргет | D2: 40
A3: 46054 | B3: Сервисы и подписки | C3: CapCut Pro | D3: 10

Sheet Цены
A1: Цена, $ | B1: Продано шт (за год) | C1: Выручка, $ | E1: Впишите цены в столбец A — увидите, сколько продано по каждой цене.
A2: 15 | B2: =IF(A2="","",SUMIFS(Продажи!$D$2:$D$5000,Продажи!$E$2:$E$5000,A2,Продажи!$A$2:$A$5000,">="&DATE(Настройки!$B$3,1,1),Продажи!$A$2:$A$5000,"<"&DATE(Настройки!$B$3+1,1,1))) | C2: =IF(A2="","",SUMIFS(Продажи!$F$2:$F$5000,Продажи!$E$2:$E$5000,A2,Продажи!$A$2:$A$5000,">="&DATE(Настройки!$B$3,1,1),Продажи!$A$2:$A$5000,"<"&DATE(Настройки!$B$3+1,1,1)))
A3: 20 | B3: =IF(A3="","",SUMIFS(Продажи!$D$2:$D$5000,Продажи!$E$2:$E$5000,A3,Продажи!$A$2:$A$5000,">="&DATE(Настройки!$B$3,1,1),Продажи!$A$2:$A$5000,"<"&DATE(Настройки!$B$3+1,1,1))) | C3: =IF(A3="","",SUMIFS(Продажи!$F$2:$F$5000,Продажи!$E$2:$E$5000,A3,Продажи!$A$2:$A$5000,">="&DATE(Настройки!$B$3,1,1),Продажи!$A$2:$A$5000,"<"&DATE(Настройки!$B$3+1,1,1)))
A4: 30 | B4: =IF(A4="","",SUMIFS(Продажи!$D$2:$D$5000,Продажи!$E$2:$E$5000,A4,Продажи!$A$2:$A$5000,">="&DATE(Настройки!$B$3,1,1),Продажи!$A$2:$A$5000,"<"&DATE(Настройки!$B$3+1,1,1))) | C4: =IF(A4="","",SUMIFS(Продажи!$F$2:$F$5000,Продажи!$E$2:$E$5000,A4,Продажи!$A$2:$A$5000,">="&DATE(Настройки!$B$3,1,1),Продажи!$A$2:$A$5000,"<"&DATE(Настройки!$B$3+1,1,1)))
B5: =IF(A5="","",SUMIFS(Продажи!$D$2:$D$5000,Продажи!$E$2:$E$5000,A5,Продажи!$A$2:$A$5000,">="&DATE(Настройки!$B$3,1,1),Продажи!$A$2:$A$5000,"<"&DATE(Настройки!$B$3+1,1,1))) | C5: =IF(A5="","",SUMIFS(Продажи!$F$2:$F$5000,Продажи!$E$2:$E$5000,A5,Продажи!$A$2:$A$5000,">="&DATE(Настройки!$B$3,1,1),Продажи!$A$2:$A$5000,"<"&DATE(Настройки!$B$3+1,1,1)))
B6: =IF(A6="","",SUMIFS(Продажи!$D$2:$D$5000,Продажи!$E$2:$E$5000,A6,Продажи!$A$2:$A$5000,">="&DATE(Настройки!$B$3,1,1),Продажи!$A$2:$A$5000,"<"&DATE(Настройки!$B$3+1,1,1))) | C6: =IF(A6="","",SUMIFS(Продажи!$F$2:$F$5000,Продажи!$E$2:$E$5000,A6,Продажи!$A$2:$A$5000,">="&DATE(Настройки!$B$3,1,1),Продажи!$A$2:$A$5000,"<"&DATE(Настройки!$B$3+1,1,1)))
B7: =IF(A7="","",SUMIFS(Продажи!$D$2:$D$5000,Продажи!$E$2:$E$5000,A7,Продажи!$A$2:$A$5000,">="&DATE(Настройки!$B$3,1,1),Продажи!$A$2:$A$5000,"<"&DATE(Настройки!$B$3+1,1,1))) | C7: =IF(A7="","",SUMIFS(Продажи!$F$2:$F$5000,Продажи!$E$2:$E$5000,A7,Продажи!$A$2:$A$5000,">="&DATE(Настройки!$B$3,1,1),Продажи!$A$2:$A$5000,"<"&DATE(Настройки!$B$3+1,1,1)))
B8: =IF(A8="","",SUMIFS(Продажи!$D$2:$D$5000,Продажи!$E$2:$E$5000,A8,Продажи!$A$2:$A$5000,">="&DATE(Настройки!$B$3,1,1),Продажи!$A$2:$A$5000,"<"&DATE(Настройки!$B$3+1,1,1))) | C8: =IF(A8="","",SUMIFS(Продажи!$F$2:$F$5000,Продажи!$E$2:$E$5000,A8,Продажи!$A$2:$A$5000,">="&DATE(Настройки!$B$3,1,1),Продажи!$A$2:$A$5000,"<"&DATE(Настройки!$B$3+1,1,1)))
B9: =IF(A9="","",SUMIFS(Продажи!$D$2:$D$5000,Продажи!$E$2:$E$5000,A9,Продажи!$A$2:$A$5000,">="&DATE(Настройки!$B$3,1,1),Продажи!$A$2:$A$5000,"<"&DATE(Настройки!$B$3+1,1,1))) | C9: =IF(A9="","",SUMIFS(Продажи!$F$2:$F$5000,Продажи!$E$2:$E$5000,A9,Продажи!$A$2:$A$5000,">="&DATE(Настройки!$B$3,1,1),Продажи!$A$2:$A$5000,"<"&DATE(Настройки!$B$3+1,1,1)))
B10: =IF(A10="","",SUMIFS(Продажи!$D$2:$D$5000,Продажи!$E$2:$E$5000,A10,Продажи!$A$2:$A$5000,">="&DATE(Настройки!$B$3,1,1),Продажи!$A$2:$A$5000,"<"&DATE(Настройки!$B$3+1,1,1))) | C10: =IF(A10="","",SUMIFS(Продажи!$F$2:$F$5000,Продажи!$E$2:$E$5000,A10,Продажи!$A$2:$A$5000,">="&DATE(Настройки!$B$3,1,1),Продажи!$A$2:$A$5000,"<"&DATE(Настройки!$B$3+1,1,1)))
B11: =IF(A11="","",SUMIFS(Продажи!$D$2:$D$5000,Продажи!$E$2:$E$5000,A11,Продажи!$A$2:$A$5000,">="&DATE(Настройки!$B$3,1,1),Продажи!$A$2:$A$5000,"<"&DATE(Настройки!$B$3+1,1,1))) | C11: =IF(A11="","",SUMIFS(Продажи!$F$2:$F$5000,Продажи!$E$2:$E$5000,A11,Продажи!$A$2:$A$5000,">="&DATE(Настройки!$B$3,1,1),Продажи!$A$2:$A$5000,"<"&DATE(Настройки!$B$3+1,1,1)))
B12: =IF(A12="","",SUMIFS(Продажи!$D$2:$D$5000,Продажи!$E$2:$E$5000,A12,Продажи!$A$2:$A$5000,">="&DATE(Настройки!$B$3,1,1),Продажи!$A$2:$A$5000,"<"&DATE(Настройки!$B$3+1,1,1))) | C12: =IF(A12="","",SUMIFS(Продажи!$F$2:$F$5000,Продажи!$E$2:$E$5000,A12,Продажи!$A$2:$A$5000,">="&DATE(Настройки!$B$3,1,1),Продажи!$A$2:$A$5000,"<"&DATE(Настройки!$B$3+1,1,1)))
B13: =IF(A13="","",SUMIFS(Продажи!$D$2:$D$5000,Продажи!$E$2:$E$5000,A13,Продажи!$A$2:$A$5000,">="&DATE(Настройки!$B$3,1,1),Продажи!$A$2:$A$5000,"<"&DATE(Настройки!$B$3+1,1,1))) | C13: =IF(A13="","",SUMIFS(Продажи!$F$2:$F$5000,Продажи!$E$2:$E$5000,A13,Продажи!$A$2:$A$5000,">="&DATE(Настройки!$B$3,1,1),Продажи!$A$2:$A$5000,"<"&DATE(Настройки!$B$3+1,1,1)))
B14: =IF(A14="","",SUMIFS(Продажи!$D$2:$D$5000,Продажи!$E$2:$E$5000,A14,Продажи!$A$2:$A$5000,">="&DATE(Настройки!$B$3,1,1),Продажи!$A$2:$A$5000,"<"&DATE(Настройки!$B$3+1,1,1))) | C14: =IF(A14="","",SUMIFS(Продажи!$F$2:$F$5000,Продажи!$E$2:$E$5000,A14,Продажи!$A$2:$A$5000,">="&DATE(Настройки!$B$3,1,1),Продажи!$A$2:$A$5000,"<"&DATE(Настройки!$B$3+1,1,1)))
B15: =IF(A15="","",SUMIFS(Продажи!$D$2:$D$5000,Продажи!$E$2:$E$5000,A15,Продажи!$A$2:$A$5000,">="&DATE(Настройки!$B$3,1,1),Продажи!$A$2:$A$5000,"<"&DATE(Настройки!$B$3+1,1,1))) | C15: =IF(A15="","",SUMIFS(Продажи!$F$2:$F$5000,Продажи!$E$2:$E$5000,A15,Продажи!$A$2:$A$5000,">="&DATE(Настройки!$B$3,1,1),Продажи!$A$2:$A$5000,"<"&DATE(Настройки!$B$3+1,1,1)))
